materialdashboard/Accordion.py
materialdashboard/AccordionActions.py
materialdashboard/AccordionDetails.py
materialdashboard/AccordionSummary.py
materialdashboard/Alert.py
materialdashboard/AlertTitle.py
materialdashboard/AppBar.py
materialdashboard/Autocomplete.py
materialdashboard/Avatar.py
materialdashboard/AvatarGroup.py
materialdashboard/Backdrop.py
materialdashboard/BackdropUnstyled.py
materialdashboard/Badge.py
materialdashboard/BadgeUnstyled.py
materialdashboard/BottomNavigation.py
materialdashboard/BottomNavigationAction.py
materialdashboard/Box.py
materialdashboard/Breadcrumbs.py
materialdashboard/Button.py
materialdashboard/ButtonBase.py
materialdashboard/ButtonGroup.py
materialdashboard/ButtonUnstyled.py
materialdashboard/Card.py
materialdashboard/CardActionArea.py
materialdashboard/CardActions.py
materialdashboard/CardContent.py
materialdashboard/CardHeader.py
materialdashboard/CardMedia.py
materialdashboard/Checkbox.py
materialdashboard/Chip.py
materialdashboard/CircularProgress.py
materialdashboard/ClickAwayListener.py
materialdashboard/Collapse.py
materialdashboard/Container.py
materialdashboard/CssBaseline.py
materialdashboard/Dialog.py
materialdashboard/DialogActions.py
materialdashboard/DialogContent.py
materialdashboard/DialogContentText.py
materialdashboard/DialogTitle.py
materialdashboard/Divider.py
materialdashboard/Drawer.py
materialdashboard/ExtendBackdropUnstyled.py
materialdashboard/ExtendBadgeUnstyled.py
materialdashboard/ExtendButton.py
materialdashboard/ExtendButtonBase.py
materialdashboard/ExtendModalUnstyled.py
materialdashboard/ExtendSliderUnstyled.py
materialdashboard/Fab.py
materialdashboard/Fade.py
materialdashboard/FilledInput.py
materialdashboard/FormControl.py
materialdashboard/FormControlLabel.py
materialdashboard/FormControlUnstyled.py
materialdashboard/FormGroup.py
materialdashboard/FormHelperText.py
materialdashboard/FormLabel.py
materialdashboard/GlobalStyles.py
materialdashboard/Grid.py
materialdashboard/Grow.py
materialdashboard-0.5.0.dist-info/LICENSE
materialdashboard-0.5.0.dist-info/METADATA
materialdashboard-0.5.0.dist-info/WHEEL
materialdashboard-0.5.0.dist-info/top_level.txt
materialdashboard-0.5.0.dist-info/RECORD
