Metadata-Version: 2.1
Name: materialdashboard
Version: 0.5.0
Summary: Dashboard with a material design
Home-page: UNKNOWN
Author: Flo Vouin <florent.vouin@gmail.com>
License: MIT
Platform: UNKNOWN
Classifier: Framework :: Dash
